requirements_detector/__init__.py
requirements_detector/__main__.py
requirements_detector/detect.py
requirements_detector/exceptions.py
requirements_detector/formatters.py
requirements_detector/handle_setup.py
requirements_detector/poetry_semver/README.md
requirements_detector/poetry_semver/__init__.py
requirements_detector/poetry_semver/empty_constraint.py
requirements_detector/poetry_semver/exceptions.py
requirements_detector/poetry_semver/patterns.py
requirements_detector/poetry_semver/version.py
requirements_detector/poetry_semver/version_constraint.py
requirements_detector/poetry_semver/version_range.py
requirements_detector/poetry_semver/version_union.py
requirements_detector/requirement.py
requirements_detector/run.py
requirements_detector-1.3.1.dist-info/LICENSE
requirements_detector-1.3.1.dist-info/METADATA
requirements_detector-1.3.1.dist-info/WHEEL
requirements_detector-1.3.1.dist-info/entry_points.txt
requirements_detector-1.3.1.dist-info/RECORD
