Metadata-Version: 2.1
Name: requirements-detector
Version: 1.3.1
Summary: Python tool to find and list requirements of a Python project
Home-page: https://github.com/landscapeio/requirements-detector
License: MIT
Keywords: python,requirements detector
Author: Landscape.io
Author-email: code@landscape.io
Requires-Python: >=3.8,<4.0
Classifier: Development Status :: 5 - Production/Stable
Classifier: Environment :: Console
Classifier: Intended Audience :: Developers
Classifier: License :: OSI Approved :: MIT License
Classifier: Operating System :: Unix
Classifier: Programming Language :: Python :: 3
Classifier: Programming Language :: Python :: 3.8
Classifier: Programming Language :: Python :: 3.9
Classifier: Programming Language :: Python :: 3.10
Classifier: Programming Language :: Python :: 3.11
Classifier: Programming Language :: Python :: 3.12
Classifier: Topic :: Software Development :: Quality Assurance
Requires-Dist: astroid (>=3.0,<4.0)
Requires-Dist: packaging (>=21.3)
Requires-Dist: semver (>=3.0.0,<4.0.0)
Requires-Dist: toml (>=0.10.2,<0.11.0)
